buildstream_plugins/__init__.py
buildstream_plugins/elements/__init__.py
buildstream_plugins/elements/autotools.py
buildstream_plugins/elements/autotools.yaml
buildstream_plugins/elements/cmake.py
buildstream_plugins/elements/cmake.yaml
buildstream_plugins/elements/make.py
buildstream_plugins/elements/make.yaml
buildstream_plugins/elements/meson.py
buildstream_plugins/elements/meson.yaml
buildstream_plugins/elements/pip.py
buildstream_plugins/elements/pip.yaml
buildstream_plugins/elements/setuptools.py
buildstream_plugins/elements/setuptools.yaml
buildstream_plugins/sourcemirrors/__init__.py
buildstream_plugins/sourcemirrors/gitlab_lfs_mirror.py
buildstream_plugins/sourcemirrors/simple_mirror.py
buildstream_plugins/sources/__init__.py
buildstream_plugins/sources/_utils.py
buildstream_plugins/sources/bzr.py
buildstream_plugins/sources/cargo.py
buildstream_plugins/sources/docker.py
buildstream_plugins/sources/git.py
buildstream_plugins/sources/patch.py
buildstream_plugins/sources/pip.py
buildstream_plugins-2.4.0.dist-info/LICENSE
buildstream_plugins-2.4.0.dist-info/METADATA
buildstream_plugins-2.4.0.dist-info/NOTICE
buildstream_plugins-2.4.0.dist-info/WHEEL
buildstream_plugins-2.4.0.dist-info/entry_points.txt
buildstream_plugins-2.4.0.dist-info/top_level.txt
buildstream_plugins-2.4.0.dist-info/RECORD
